precice_config_check-1.0.2.dist-info/licenses/LICENSE
preciceconfigcheck/cli.py
preciceconfigcheck/color.py
preciceconfigcheck/rule.py
preciceconfigcheck/rule_utils.py
preciceconfigcheck/rules_processing.py
preciceconfigcheck/severity.py
preciceconfigcheck/violation.py
preciceconfigcheck/rules/compositional_coupling.py
preciceconfigcheck/rules/coupling_scheme_mapping.py
preciceconfigcheck/rules/data_use_read_write.py
preciceconfigcheck/rules/disjoint_simulations.py
preciceconfigcheck/rules/m2n_exchange.py
preciceconfigcheck/rules/mapping.py
preciceconfigcheck/rules/missing_coupling.py
preciceconfigcheck/rules/missing_exchange.py
preciceconfigcheck/rules/provide_mesh.py
preciceconfigcheck/rules/receive_mesh.py
precice_config_check-1.0.2.dist-info/METADATA
precice_config_check-1.0.2.dist-info/WHEEL
precice_config_check-1.0.2.dist-info/entry_points.txt
precice_config_check-1.0.2.dist-info/top_level.txt
precice_config_check-1.0.2.dist-info/RECORD
