Metadata-Version: 2.4
Name: precice-config-check
Version: 1.0.2
License-Expression: MIT
Project-URL: Repository, https://github.com/precice-forschungsprojekt/config-check.git
Project-URL: Issues, https://github.com/precice-forschungsprojekt/config-check/issues
Requires-Python: >=3.10
License-File: LICENSE
Requires-Dist: precice-config-graph
Dynamic: license-file
